[
    {
        "id": 1773753376126,
        "name": "Nature 期刊精选图表色 (NPG)",
        "colors": [
            "#E64B35",
            "#4DBBD5",
            "#00A087",
            "#3C5488",
            "#F39B7F",
            "#8491B4",
            "#91D1C2"
        ]
    },
    {
        "id": 1773753376127,
        "name": "Gut Microbiota (肠道菌群主流分组)",
        "colors": [
            "#2CA02C",
            "#1F77B4",
            "#FF7F0E",
            "#D62728",
            "#9467BD"
        ]
    },
    {
        "id": 1773753376128,
        "name": "Molecular Docking (结合能热图渐变)",
        "colors": [
            "#4575B4",
            "#91BFDB",
            "#E0F3F8",
            "#FEE090",
            "#FC8D59",
            "#D73027"
        ]
    },
    {
        "id": 1773755268976,
        "name": "我自己定义的",
        "colors": [
            "#2563eb",
            "#38bdf8",
            "#818cf8",
            "#C41717",
            "#146A80"
        ]
    },
    {
        "id": 1773755272899,
        "name": "这是啥颜色",
        "colors": [
            "#2563eb",
            "#C71A99",
            "#DA1B1B",
            "#3C9F8B"
        ]
    }
]